bits/__init__.py
bits/swoogo/__init__.py
bits_swoogo-1.0.1.dist-info/METADATA
bits_swoogo-1.0.1.dist-info/WHEEL
bits_swoogo-1.0.1.dist-info/top_level.txt
bits_swoogo-1.0.1.dist-info/RECORD
