Metadata-Version: 2.1
Name: bits-swoogo
Version: 1.0.1
Summary: BITS Swoogo
Home-page: UNKNOWN
Author: Lukas Karlsson
Author-email: karlsson@broadinstitute.org
License: Apache Software License
Platform: UNKNOWN
